[{
  "_id": {
    "$oid": "60d80a3dc12ca91ab40f924e"
  },
  "order": 1,
  "course": {
    "$oid": "60d80a3dc12ca91ab40f924a"
  },
  "title": "Getting Started",
  "__v": 0
},{
  "_id": {
    "$oid": "60d80a3dc12ca91ab40f924f"
  },
  "order": 2,
  "course": {
    "$oid": "60d80a3dc12ca91ab40f924a"
  },
  "title": "Introductin to Atributes",
  "__v": 0
},{
  "_id": {
    "$oid": "60d80a3dc12ca91ab40f9252"
  },
  "order": 1,
  "course": {
    "$oid": "60d80a3dc12ca91ab40f924b"
  },
  "title": "Introduction",
  "__v": 0
},{
  "_id": {
    "$oid": "60d80a3dc12ca91ab40f9253"
  },
  "order": 2,
  "course": {
    "$oid": "60d80a3dc12ca91ab40f924b"
  },
  "title": "Getting Started",
  "__v": 0
},{
  "_id": {
    "$oid": "60d80a3dc12ca91ab40f9240"
  },
  "order": 1,
  "course": {
    "$oid": "60d80a3dc12ca91ab40f923c"
  },
  "title": "Asynchronous Patterns",
  "__v": 0
}]